ocr_common_api_example/__init__.py
ocr_common_api_example/example.py
ocr_common_api_example-0.0.2.dist-info/LICENSE
ocr_common_api_example-0.0.2.dist-info/METADATA
ocr_common_api_example-0.0.2.dist-info/WHEEL
ocr_common_api_example-0.0.2.dist-info/top_level.txt
ocr_common_api_example-0.0.2.dist-info/RECORD
